music_metadata_edi-20.8-py3.8-nspkg.pth
music_metadata/edi/__init__.py
music_metadata/edi/errors.py
music_metadata/edi/fields.py
music_metadata/edi/file.py
music_metadata/edi/records.py
music_metadata/edi/transactions.py
music_metadata/edi/tests/CW190001MPC_000.V21
music_metadata/edi/tests/CW190008MPC_0000_V3-0-0.ISR
music_metadata/edi/tests/__init__.py
music_metadata_edi-20.8.dist-info/LICENSE
music_metadata_edi-20.8.dist-info/METADATA
music_metadata_edi-20.8.dist-info/WHEEL
music_metadata_edi-20.8.dist-info/namespace_packages.txt
music_metadata_edi-20.8.dist-info/top_level.txt
music_metadata_edi-20.8.dist-info/RECORD
