Metadata-Version: 2.1
Name: music-metadata-edi
Version: 20.8
Summary: Music Metedata - EDI-based formats
Home-page: https://github.com/musicmetadata/territories
Author: Matija Kolarić
Author-email: matijakolaric@users.noreply.github.com
License: UNKNOWN
Platform: UNKNOWN
Classifier: Programming Language :: Python :: 3
Classifier: Programming Language :: Python :: 3.7
Classifier: License :: OSI Approved :: MIT License
Classifier: Operating System :: OS Independent
Requires-Python: >=3.7
